chloroscan/__init__.py
chloroscan/cli/__init__.py
chloroscan/config/ChloroScan.init.yaml
chloroscan/config/ChloroScan.snk.yaml
chloroscan/config/config.TARA.yaml
chloroscan/config/config.default.yaml
chloroscan/config/config.paper.yaml
chloroscan/config/config.template.yaml
chloroscan/config/config.zero.yaml
chloroscan/snk.yaml
chloroscan/workflow/Snakefile
chloroscan/workflow/__init__.py
chloroscan/workflow/envs/CAT_env.yml
chloroscan/workflow/envs/DepthCall.yml
chloroscan/workflow/envs/binny.post-deploy.sh
chloroscan/workflow/envs/binny.yml
chloroscan/workflow/envs/corgi_env.yml
chloroscan/workflow/envs/documenting_binny.yml
chloroscan/workflow/envs/gffread.post-deploy.sh
chloroscan/workflow/envs/gffread.yml
chloroscan/workflow/envs/krona.post-deploy.sh
chloroscan/workflow/envs/krona.yml
chloroscan/workflow/envs/prep_anvio.yml
chloroscan/workflow/envs/refinement.yml
chloroscan/workflow/envs/visualization.yml
chloroscan/workflow/scripts/calcAvgCoverage.pl
chloroscan/workflow/scripts/call_contig_depth.sh
chloroscan/workflow/scripts/cds-extraction.sh
chloroscan/workflow/scripts/corgi-fasta_filter.py
chloroscan/workflow/scripts/corgi-gather_accession.sh
chloroscan/workflow/scripts/create_taxonomy_profile.py
chloroscan/workflow/scripts/create_yaml.sh
chloroscan/workflow/scripts/merge_contig_depth.sh
chloroscan/workflow/scripts/new_corgi_gather_accession.sh
chloroscan/workflow/scripts/refine_bins.py
chloroscan/workflow/scripts/summarization_utils.py
chloroscan/workflow/scripts/summarize_binny_results.py
chloroscan/workflow/scripts/visualization.py
chloroscan/workflow/scripts/visualization_utils.py
chloroscan-0.1.5.dist-info/METADATA
chloroscan-0.1.5.dist-info/WHEEL
chloroscan-0.1.5.dist-info/entry_points.txt
chloroscan-0.1.5.dist-info/licenses/LICENSE
chloroscan-0.1.5.dist-info/RECORD
