Metadata-Version: 2.4
Name: chloroscan
Version: 0.1.5
Summary: A computational workflow designed to recover plastid genomes from metagenomes.
License: Apache-2.0
License-File: LICENSE
Author: Andy Tong, Robert Turnbull, Vanessa Rossetto Marcelino, Heroen Verbruggen
Requires-Python: >=3.9,<4.0
Classifier: License :: OSI Approved :: Apache Software License
Classifier: Programming Language :: Python :: 3
Classifier: Programming Language :: Python :: 3.9
Classifier: Programming Language :: Python :: 3.10
Classifier: Programming Language :: Python :: 3.11
Classifier: Programming Language :: Python :: 3.12
Classifier: Programming Language :: Python :: 3.13
Classifier: Programming Language :: Python :: 3.14
Requires-Dist: click (<8)
Requires-Dist: gitpython (>=3.1.32,<4.0.0)
Requires-Dist: numpy (>1.24.4,<2)
Requires-Dist: pandas (>=2.0)
Requires-Dist: snk-cli (>=0.1.2,<0.2.0)
